dnneasyensemble/__init__.py
dnneasyensemble/dnneasyensemble.py
dnneasyensemble-0.0.1.dist-info/METADATA
dnneasyensemble-0.0.1.dist-info/WHEEL
dnneasyensemble-0.0.1.dist-info/top_level.txt
dnneasyensemble-0.0.1.dist-info/RECORD
